ptytest/__init__.py
ptytest/keys.py
ptytest/pytest_plugin.py
ptytest/session.py
ptytest-0.1.0.dist-info/METADATA
ptytest-0.1.0.dist-info/WHEEL
ptytest-0.1.0.dist-info/entry_points.txt
ptytest-0.1.0.dist-info/licenses/LICENSE
ptytest-0.1.0.dist-info/RECORD
