Metadata-Version: 2.4
Name: ptytest
Version: 0.1.0
Summary: Real terminal testing framework - test interactive CLI apps with actual keystrokes
Project-URL: Homepage, https://github.com/brandon-fryslie/ptytest
Project-URL: Repository, https://github.com/brandon-fryslie/ptytest
Project-URL: Documentation, https://github.com/brandon-fryslie/ptytest#readme
Author: Brandon Fryslie
License-Expression: MIT
License-File: LICENSE
Keywords: cli,interactive,pexpect,pty,terminal,testing,tmux,zle,zsh
Classifier: Development Status :: 4 - Beta
Classifier: Environment :: Console
Classifier: Framework :: Pytest
Classifier: Intended Audience :: Developers
Classifier: License :: OSI Approved :: MIT License
Classifier: Operating System :: MacOS
Classifier: Operating System :: POSIX :: Linux
Classifier: Programming Language :: Python :: 3
Classifier: Programming Language :: Python :: 3.8
Classifier: Programming Language :: Python :: 3.9
Classifier: Programming Language :: Python :: 3.10
Classifier: Programming Language :: Python :: 3.11
Classifier: Programming Language :: Python :: 3.12
Classifier: Topic :: Software Development :: Testing
Classifier: Topic :: System :: Shells
Classifier: Topic :: Terminals
Requires-Python: >=3.8
Requires-Dist: pexpect>=4.8.0
Provides-Extra: dev
Requires-Dist: mypy>=1.0.0; extra == 'dev'
Requires-Dist: pytest-timeout>=2.0.0; extra == 'dev'
Requires-Dist: pytest>=7.0.0; extra == 'dev'
Requires-Dist: ruff>=0.1.0; extra == 'dev'
Provides-Extra: test
Requires-Dist: pytest-timeout>=2.0.0; extra == 'test'
Requires-Dist: pytest>=7.0.0; extra == 'test'
